Workbook

Sheet Historical_Data
A1: COTMX Historical Data
A2: Month | B2: Revenue | C2: COGS | D2: Operating_Expenses | E2: Marketing | F2: Other_Expenses
A3: 44927 | B3: 355000 | C3: 142000 | D3: 84000 | E3: 32000 | F3: 18000
A4: 44958 | B4: 368000 | C4: 148000 | D4: 85000 | E4: 34000 | F4: 19000
A5: 44986 | B5: 382000 | C5: 153000 | D5: 87000 | E5: 35000 | F5: 20000
A6: 45017 | B6: 394000 | C6: 158000 | D6: 90000 | E6: 36000 | F6: 21000
A7: 45047 | B7: 405000 | C7: 164000 | D7: 92000 | E7: 37000 | F7: 22000
A8: 45078 | B8: 420000 | C8: 170000 | D8: 93000 | E8: 38000 | F8: 23000
A9: 45108 | B9: 432000 | C9: 175000 | D9: 95000 | E9: 39000 | F9: 24000
A10: 45139 | B10: 448000 | C10: 182000 | D10: 97000 | E10: 40000 | F10: 24500
A11: 45170 | B11: 462000 | C11: 190000 | D11: 99000 | E11: 41000 | F11: 25000
A12: 45200 | B12: 475000 | C12: 197000 | D12: 101000 | E12: 42000 | F12: 26000
A13: 45231 | B13: 490000 | C13: 205000 | D13: 103000 | E13: 43000 | F13: 27000
A14: 45261 | B14: 505000 | C14: 212000 | D14: 105000 | E14: 44000 | F14: 28000

Sheet Assumptions
A1: ASSUMPTIONS
A2: Parameter | B2: Value
A3: Revenue Growth Rate | B3: 0.04
A4: COGS % of Revenue | B4: 0.4
A5: Operating Expense Growth | B5: 0.02
A6: Marketing % of Revenue | B6: 0.08
A7: Other Expenses % | B7: 0.05
A8: Tax Rate | B8: 0.25
A9: Profit Target | B9: 60000000

Sheet Forecast_2024
A1: COTMX FORECAST ASUMPTION DATA
A2: Month | B2: Revenue | C2: COGS | D2: Operating Expenses | E2: Marketing | F2: Other expenses | G2: Gross Profit | H2: EBITDA | I2: Depreaciation | J2: Intrest | K2: EBT | L2: Taxes | M2: Net Income
A3: 45292 | B3: =_xlfn.XLOOKUP(Historical_Data!A14,Historical_Data!A:A,Historical_Data!B:B)*(1+Assumptions!B3) -> 525200 | C3: =B3*Assumptions!$B$4 -> 210080 | D3: =B3*Assumptions!$B$5 -> 10504 | E3: =B3*Assumptions!$B$6 -> 42016 | F3: =B3*Assumptions!$B$7 -> 26260 | G3: =B3-C3 -> 315120 | H3: =G3-(D3+E3+F3) -> 236340 | I3: 15000 | J3: 8000 | K3: =H3 - I3 - J3 -> 213340 | L3: =B3*Assumptions!$B$8 -> 131300 | M3: =K3 - L3 -> 82040
A4: 45323 | B4: =B3*(1+Assumptions!$B$3) -> 546208 | C4: =B4*Assumptions!$B$4 -> 218483.2 | D4: =B4*Assumptions!$B$5 -> 10924.16 | E4: =B4*Assumptions!$B$6 -> 43696.64 | F4: =B4*Assumptions!$B$7 -> 27310.4 | G4: =B4-C4 -> 327724.8 | H4: =G4-(D4+E4+F4) -> 245793.6 | I4: 15000 | J4: 8000 | K4: =H4 - I4 - J4 -> 222793.6 | L4: =B4*Assumptions!$B$8 -> 136552 | M4: =K4 - L4 -> 86241.6
A5: 45352 | B5: =B4*(1+Assumptions!$B$3) -> 568056.32 | C5: =B5*Assumptions!$B$4 -> 227222.53 | D5: =B5*Assumptions!$B$5 -> 11361.126 | E5: =B5*Assumptions!$B$6 -> 45444.506 | F5: =B5*Assumptions!$B$7 -> 28402.816 | G5: =B5-C5 -> 340833.79 | H5: =G5-(D5+E5+F5) -> 255625.34 | I5: 15000 | J5: 8000 | K5: =H5 - I5 - J5 -> 232625.34 | L5: =B5*Assumptions!$B$8 -> 142014.08 | M5: =K5 - L5 -> 90611.264
A6: 45383 | B6: =B5*(1+Assumptions!$B$3) -> 590778.57 | C6: =B6*Assumptions!$B$4 -> 236311.43 | D6: =B6*Assumptions!$B$5 -> 11815.571 | E6: =B6*Assumptions!$B$6 -> 47262.286 | F6: =B6*Assumptions!$B$7 -> 29538.929 | G6: =B6-C6 -> 354467.14 | H6: =G6-(D6+E6+F6) -> 265850.36 | I6: 15000 | J6: 8000 | K6: =H6 - I6 - J6 -> 242850.36 | L6: =B6*Assumptions!$B$8 -> 147694.64 | M6: =K6 - L6 -> 95155.715
A7: 45413 | B7: =B6*(1+Assumptions!$B$3) -> 614409.72 | C7: =B7*Assumptions!$B$4 -> 245763.89 | D7: =B7*Assumptions!$B$5 -> 12288.194 | E7: =B7*Assumptions!$B$6 -> 49152.777 | F7: =B7*Assumptions!$B$7 -> 30720.486 | G7: =B7-C7 -> 368645.83 | H7: =G7-(D7+E7+F7) -> 276484.37 | I7: 15000 | J7: 8000 | K7: =H7 - I7 - J7 -> 253484.37 | L7: =B7*Assumptions!$B$8 -> 153602.43 | M7: =K7 - L7 -> 99881.943
A8: 45444 | B8: =B7*(1+Assumptions!$B$3) -> 638986.1 | C8: =B8*Assumptions!$B$4 -> 255594.44 | D8: =B8*Assumptions!$B$5 -> 12779.722 | E8: =B8*Assumptions!$B$6 -> 51118.888 | F8: =B8*Assumptions!$B$7 -> 31949.305 | G8: =B8-C8 -> 383391.66 | H8: =G8-(D8+E8+F8) -> 287543.75 | I8: 15000 | J8: 8000 | K8: =H8 - I8 - J8 -> 264543.75 | L8: =B8*Assumptions!$B$8 -> 159746.53 | M8: =K8 - L8 -> 104797.22
A9: 45474 | B9: =B8*(1+Assumptions!$B$3) -> 664545.55 | C9: =B9*Assumptions!$B$4 -> 265818.22 | D9: =B9*Assumptions!$B$5 -> 13290.911 | E9: =B9*Assumptions!$B$6 -> 53163.644 | F9: =B9*Assumptions!$B$7 -> 33227.277 | G9: =B9-C9 -> 398727.33 | H9: =G9-(D9+E9+F9) -> 299045.5 | I9: 15000 | J9: 8000 | K9: =H9 - I9 - J9 -> 276045.5 | L9: =B9*Assumptions!$B$8 -> 166136.39 | M9: =K9 - L9 -> 109909.11
A10: 45505 | B10: =B9*(1+Assumptions!$B$3) -> 691127.37 | C10: =B10*Assumptions!$B$4 -> 276450.95 | D10: =B10*Assumptions!$B$5 -> 13822.547 | E10: =B10*Assumptions!$B$6 -> 55290.19 | F10: =B10*Assumptions!$B$7 -> 34556.369 | G10: =B10-C10 -> 414676.42 | H10: =G10-(D10+E10+F10) -> 311007.32 | I10: 15000 | J10: 8000 | K10: =H10 - I10 - J10 -> 288007.32 | L10: =B10*Assumptions!$B$8 -> 172781.84 | M10: =K10 - L10 -> 115225.47
A11: 45536 | B11: =B10*(1+Assumptions!$B$3) -> 718772.47 | C11: =B11*Assumptions!$B$4 -> 287508.99 | D11: =B11*Assumptions!$B$5 -> 14375.449 | E11: =B11*Assumptions!$B$6 -> 57501.797 | F11: =B11*Assumptions!$B$7 -> 35938.623 | G11: =B11-C11 -> 431263.48 | H11: =G11-(D11+E11+F11) -> 323447.61 | I11: 15000 | J11: 8000 | K11: =H11 - I11 - J11 -> 300447.61 | L11: =B11*Assumptions!$B$8 -> 179693.12 | M11: =K11 - L11 -> 120754.49
A12: 45566 | B12: =B11*(1+Assumptions!$B$3) -> 747523.36 | C12: =B12*Assumptions!$B$4 -> 299009.35 | D12: =B12*Assumptions!$B$5 -> 14950.467 | E12: =B12*Assumptions!$B$6 -> 59801.869 | F12: =B12*Assumptions!$B$7 -> 37376.168 | G12: =B12-C12 -> 448514.02 | H12: =G12-(D12+E12+F12) -> 336385.51 | I12: 15000 | J12: 8000 | K12: =H12 - I12 - J12 -> 313385.51 | L12: =B12*Assumptions!$B$8 -> 186880.84 | M12: =K12 - L12 -> 126504.67
A13: 45597 | B13: =B12*(1+Assumptions!$B$3) -> 777424.3 | C13: =B13*Assumptions!$B$4 -> 310969.72 | D13: =B13*Assumptions!$B$5 -> 15548.486 | E13: =B13*Assumptions!$B$6 -> 62193.944 | F13: =B13*Assumptions!$B$7 -> 38871.215 | G13: =B13-C13 -> 466454.58 | H13: =G13-(D13+E13+F13) -> 349840.93 | I13: 15000 | J13: 8000 | K13: =H13 - I13 - J13 -> 326840.93 | L13: =B13*Assumptions!$B$8 -> 194356.07 | M13: =K13 - L13 -> 132484.86
A14: 45627 | B14: =B13*(1+Assumptions!$B$3) -> 808521.27 | C14: =B14*Assumptions!$B$4 -> 323408.51 | D14: =B14*Assumptions!$B$5 -> 16170.425 | E14: =B14*Assumptions!$B$6 -> 64681.702 | F14: =B14*Assumptions!$B$7 -> 40426.064 | G14: =B14-C14 -> 485112.76 | H14: =G14-(D14+E14+F14) -> 363834.57 | I14: 15000 | J14: 8000 | K14: =H14 - I14 - J14 -> 340834.57 | L14: =B14*Assumptions!$B$8 -> 202130.32 | M14: =K14 - L14 -> 138704.25
B18: Total Revenue Assumption | G18: Total Gross Profit Asumps | M18: Total Net Income
B19: =SUM(B3:B14) -> 7891553 | G19: =SUM(Forecast_2024!G3:G14) -> 4734931.8 | H19: =SUM(Forecast_2024!H3:H14) / SUM(Forecast_2024!B3:B14) -> 0.45 | M19: =SUM(Forecast_2024!M3:M14) -> 1302310.6
B22: Monthly Avg Revenue
B23: =AVERAGE(Forecast_2024!B3:B14) -> 657629.42 | M23: Net Profiy Margin
M24: =SUM(Forecast_2024!M7:M18) / SUM(Forecast_2024!B7:B18) -> 0.16749869
A26: =_xlfn.XLOOKUP(MIN(Forecast_2024!M3:M14), Forecast_2024!M3:M14, Forecast_2024!A3:A14) -> 45292
A27: =_xlfn.XLOOKUP(MAX(Forecast_2024!B3:B14), Forecast_2024!B3:B14, Forecast_2024!A3:A14) -> 45627

Sheet Table Wise Distribution
B2: Overall Total Valuation Estimations
B3: Sum of Revenue | C3: Sum of Gross Profit | D3: Sum of Net Income | E3: Sum of EBITDA | F3: EBITDA MARGIN | G3: NET Income MARGIN
B4: 7891553 | C4: 4734931.8 | D4: 1302310.6 | E4: 3551198.9 | F4: =GETPIVOTDATA("EBITDA",$E$3)/GETPIVOTDATA("Revenue",$B$3) -> 0.45 | G4: =GETPIVOTDATA("Net Income",$D$3)/GETPIVOTDATA("Revenue",$B$3) -> 0.1650259
B5: =GETPIVOTDATA("Revenue",$B$3) -> 7891553 | C5: =GETPIVOTDATA("Gross Profit",$C$3) -> 4734931.8 | D5: =GETPIVOTDATA("Net Income",$D$3) -> 1302310.6 | E5: =GETPIVOTDATA("EBITDA",$E$3) -> 3551198.9
B7: Total Revenue Estimation Over Year(2024) | E7: Total Reveune and COGS Distribution | I7: Distribution of Gross Profit/ EBITDA & Net Income
B8: 2024 Year | C8: Sum of Revenue | E8: 2024 Year | F8: Total Revenue | G8: Total COGS | I8: 2024 Year | J8: Sum of Gross Profit | K8: Sum of EBITDA | L8: Sum of Net Income
B9: Jan | C9: 525200 | E9: Jan | F9: 525200 | G9: 210080 | I9: Jan | J9: 315120 | K9: 236340 | L9: 82040
B10: Feb | C10: 546208 | E10: Feb | F10: 546208 | G10: 218483.2 | I10: Feb | J10: 327724.8 | K10: 245793.6 | L10: 86241.6
B11: Mar | C11: 568056.32 | E11: Mar | F11: 568056.32 | G11: 227222.53 | I11: Mar | J11: 340833.79 | K11: 255625.34 | L11: 90611.264
B12: Apr | C12: 590778.57 | E12: Apr | F12: 590778.57 | G12: 236311.43 | I12: Apr | J12: 354467.14 | K12: 265850.36 | L12: 95155.715
B13: May | C13: 614409.72 | E13: May | F13: 614409.72 | G13: 245763.89 | I13: May | J13: 368645.83 | K13: 276484.37 | L13: 99881.943
B14: Jun | C14: 638986.1 | E14: Jun | F14: 638986.1 | G14: 255594.44 | I14: Jun | J14: 383391.66 | K14: 287543.75 | L14: 104797.22
B15: Jul | C15: 664545.55 | E15: Jul | F15: 664545.55 | G15: 265818.22 | I15: Jul | J15: 398727.33 | K15: 299045.5 | L15: 109909.11
B16: Aug | C16: 691127.37 | E16: Aug | F16: 691127.37 | G16: 276450.95 | I16: Aug | J16: 414676.42 | K16: 311007.32 | L16: 115225.47
B17: Sep | C17: 718772.47 | E17: Sep | F17: 718772.47 | G17: 287508.99 | I17: Sep | J17: 431263.48 | K17: 323447.61 | L17: 120754.49
B18: Oct | C18: 747523.36 | E18: Oct | F18: 747523.36 | G18: 299009.35 | I18: Oct | J18: 448514.02 | K18: 336385.51 | L18: 126504.67
B19: Nov | C19: 777424.3 | E19: Nov | F19: 777424.3 | G19: 310969.72 | I19: Nov | J19: 466454.58 | K19: 349840.93 | L19: 132484.86
B20: Dec | C20: 808521.27 | E20: Dec | F20: 808521.27 | G20: 323408.51 | I20: Dec | J20: 485112.76 | K20: 363834.57 | L20: 138704.25
B21: Grand Total | C21: 7891553 | E21: Grand Total | F21: 7891553 | G21: 3156621.2 | I21: Grand Total | J21: 4734931.8 | K21: 3551198.9 | L21: 1302310.6
B60: Sum of Revenue | C60: Sum of COGS | D60: Sum of Gross Profit | E60: Sum of Net Income
B61: 7891553 | C61: 3156621.2 | D61: 4734931.8 | E61: 1302310.6
B65: Total | C65: Value
B66: Total Revenue | C66: =GETPIVOTDATA("Sum of Revenue",$B$60) -> 7891553
B67: Total COGS | C67: =GETPIVOTDATA("Sum of COGS",$B$60) -> 3156621.2
B68: Total Gross Profit | C68: =GETPIVOTDATA("Sum of Gross Profit",$B$60) -> 4734931.8
B69: Total Net Income | C69: =GETPIVOTDATA("Sum of Net Income",$B$60) -> 1302310.6

Sheet Dashboard
